test/__init__.py
test/test.py
tripayclient/__init__.py
tripayclient/tripay.py
tripayclient/core/__init__.py
tripayclient/core/auth.py
tripayclient/core/calculator.py
tripayclient/core/closed_transactions.py
tripayclient/core/exceptions.py
tripayclient/core/instructions.py
tripayclient/core/open_transactions.py
tripayclient/schemas/__init__.py
tripayclient/schemas/channel_enum.py
tripay_sdk-0.1.0.dist-info/LICENSE
tripay_sdk-0.1.0.dist-info/METADATA
tripay_sdk-0.1.0.dist-info/WHEEL
tripay_sdk-0.1.0.dist-info/top_level.txt
tripay_sdk-0.1.0.dist-info/RECORD
