Metadata-Version: 2.1
Name: tripay-sdk
Version: 0.1.0
Summary: Unofficial SDK for Tripay payment gateway
Home-page: https://github.com/adriyansyahmf/tripay-sdk
Author: adriyansyahmf
Author-email: adriyansyahmf0@gmail.com
License: MIT
Classifier: Development Status :: 3 - Alpha
Classifier: Intended Audience :: Developers
Classifier: License :: OSI Approved :: MIT License
Classifier: Programming Language :: Python :: 3.9
Classifier: Programming Language :: Python :: 3 :: Only
Classifier: Topic :: Software Development :: Libraries :: Python Modules
Requires-Python: >=3.9
License-File: LICENSE
Requires-Dist: attrs ==22.1.0
Requires-Dist: httpx ==0.27.0
